scraprr-0.1.14.dist-info/METADATA
scraprr-0.1.14.dist-info/WHEEL
scraprr.libs/libcrypto-f37b23c6.so.3
scraprr.libs/libssl-e2e3a021.so.3
scraprr/__init__.py
scraprr/scraprr.cpython-313-x86_64-linux-gnu.so
scraprr-0.1.14.dist-info/RECORD
