Metadata-Version: 2.4
Name: scraprr
Version: 0.1.14
Classifier: Programming Language :: Python :: 3
Classifier: Programming Language :: Python :: 3.7
Classifier: Programming Language :: Python :: 3.8
Classifier: Programming Language :: Python :: 3.9
Classifier: Programming Language :: Python :: 3.10
Classifier: Programming Language :: Python :: 3.11
Classifier: Programming Language :: Python :: 3.12
Classifier: Programming Language :: Python :: 3.13
Summary: a Rust-based web scraping library for Python
Author-email: Dariush Ghassemieh <dariush@ghassemieh.com>
License: MIT
Requires-Python: >=3.7
